aiomsg/__init__.py
aiomsg/header.py
aiomsg/msgproto.py
aiomsg/version_utils.py
aiomsg-2019.12.3.dist-info/LICENSE
aiomsg-2019.12.3.dist-info/METADATA
aiomsg-2019.12.3.dist-info/WHEEL
aiomsg-2019.12.3.dist-info/top_level.txt
aiomsg-2019.12.3.dist-info/RECORD
