Metadata-Version: 2.1
Name: aiomsg
Version: 2019.12.3
Summary: Socket-based abstraction for messaging patterns
Home-page: https://github.com/cjrh/aiomsg
Author: Caleb Hattingh
Author-email: caleb.hattingh@gmail.com
License: UNKNOWN
Keywords: asyncio socket network
Platform: UNKNOWN
Classifier: Development Status :: 3 - Alpha
Classifier: Intended Audience :: Developers
Classifier: Topic :: Software Development :: Build Tools
Classifier: License :: OSI Approved :: Apache Software License
Classifier: Programming Language :: Python :: 3.6
Classifier: Programming Language :: Python :: 3.7
Classifier: Programming Language :: Python :: 3.8
Classifier: Framework :: AsyncIO
Classifier: Topic :: Communications
Provides-Extra: all
Requires-Dist: colorama ; extra == 'all'
Requires-Dist: wheel ; extra == 'all'
Requires-Dist: pytest ; extra == 'all'
Requires-Dist: pytest-cov ; extra == 'all'
Requires-Dist: twine ; extra == 'all'
Requires-Dist: pygments ; extra == 'all'
Requires-Dist: check-manifest ; extra == 'all'
Requires-Dist: aiorun ; extra == 'all'
Requires-Dist: pytest-benchmark ; extra == 'all'
Requires-Dist: sphinx ; extra == 'all'
Requires-Dist: portpicker ; extra == 'all'
Provides-Extra: dev
Requires-Dist: check-manifest ; extra == 'dev'
Requires-Dist: colorama ; extra == 'dev'
Requires-Dist: pygments ; extra == 'dev'
Requires-Dist: twine ; extra == 'dev'
Requires-Dist: wheel ; extra == 'dev'
Requires-Dist: aiorun ; extra == 'dev'
Provides-Extra: doc
Requires-Dist: sphinx ; extra == 'doc'
Provides-Extra: test
Requires-Dist: pytest ; extra == 'test'
Requires-Dist: pytest-cov ; extra == 'test'
Requires-Dist: portpicker ; extra == 'test'
Requires-Dist: pytest-benchmark ; extra == 'test'
